odoo/addons/stock_dynamic_routing_checkout_sync/README.rst
odoo/addons/stock_dynamic_routing_checkout_sync/__init__.py
odoo/addons/stock_dynamic_routing_checkout_sync/__manifest__.py
odoo/addons/stock_dynamic_routing_checkout_sync/models/__init__.py
odoo/addons/stock_dynamic_routing_checkout_sync/readme/CONTRIBUTORS.rst
odoo/addons/stock_dynamic_routing_checkout_sync/readme/DESCRIPTION.rst
odoo/addons/stock_dynamic_routing_checkout_sync/static/description/icon.png
odoo/addons/stock_dynamic_routing_checkout_sync/static/description/index.html
odoo/addons/stock_dynamic_routing_checkout_sync/tests/__init__.py
odoo/addons/stock_dynamic_routing_checkout_sync/tests/test_routing_sync.py
odoo13_addon_stock_dynamic_routing_checkout_sync-13.0.1.1.0.dist-info/METADATA
odoo13_addon_stock_dynamic_routing_checkout_sync-13.0.1.1.0.dist-info/WHEEL
odoo13_addon_stock_dynamic_routing_checkout_sync-13.0.1.1.0.dist-info/top_level.txt
odoo13_addon_stock_dynamic_routing_checkout_sync-13.0.1.1.0.dist-info/RECORD
